dumpx0/__init__.py
dumpx0/index.py
dumpx0-0.1.dist-info/METADATA
dumpx0-0.1.dist-info/WHEEL
dumpx0-0.1.dist-info/top_level.txt
dumpx0-0.1.dist-info/RECORD
